pyvast_threatbus/__init__.py
pyvast_threatbus/message_mapping.py
pyvast_threatbus/metrics.py
pyvast_threatbus/pyvast_threatbus.py
pyvast_threatbus/test_message_mapping.py
pyvast_threatbus/test_metrics.py
pyvast_threatbus-2021.7.29.dist-info/METADATA
pyvast_threatbus-2021.7.29.dist-info/WHEEL
pyvast_threatbus-2021.7.29.dist-info/entry_points.txt
pyvast_threatbus-2021.7.29.dist-info/top_level.txt
pyvast_threatbus-2021.7.29.dist-info/RECORD
